hargreaves_lansdown_client/HLClient.py
hargreaves_lansdown_client/__init__.py
hargreaves_lansdown_client-0.0.2.dist-info/LICENSE
hargreaves_lansdown_client-0.0.2.dist-info/METADATA
hargreaves_lansdown_client-0.0.2.dist-info/WHEEL
hargreaves_lansdown_client-0.0.2.dist-info/top_level.txt
hargreaves_lansdown_client-0.0.2.dist-info/RECORD
