Metadata-Version: 2.1
Name: hargreaves-lansdown-client
Version: 0.0.2
Summary: A small client to connect to Hargreaves Lansdown
Author-email: Jack Madeley <jm@jackmadeley.co.uk>
Project-URL: Homepage, https://github.com/JackMadeley/hargreaves-lansdown-client
Project-URL: Bug Tracker, https://github.com/JackMadeley/hargreaves-lansdown-client/issues
Classifier: Programming Language :: Python :: 3
Classifier: License :: OSI Approved :: MIT License
Classifier: Operating System :: OS Independent
Requires-Python: >=3.7
License-File: LICENSE
